plateviz/__init__.py
plateviz/plateviz.py
plateviz/resources/Goldilocks.json
plateviz/resources/LICENSE.raleway.txt
plateviz/resources/Raleway-Regular.ttf
plateviz/resources/Raleway-VariableFont_wght.ttf
plateviz/resources/example_data.txt
plateviz/resources/main.png
plateviz-0.1.1.dist-info/METADATA
plateviz-0.1.1.dist-info/WHEEL
plateviz-0.1.1.dist-info/licenses/LICENSE
plateviz-0.1.1.dist-info/RECORD
