Metadata-Version: 2.4
Name: plateviz
Version: 0.1.1
Summary: An interactive visualization tool for microplate reader growth data.
Project-URL: Homepage, https://github.com/Radium2000/plateviz
Project-URL: Issues, https://github.com/Radium2000/plateviz/issues
Author-email: Rudra Kalra <rudrakalra20@gmail.com>
License-File: LICENSE
Classifier: Development Status :: 4 - Beta
Classifier: License :: OSI Approved :: MIT License
Classifier: Operating System :: Microsoft :: Windows
Classifier: Operating System :: POSIX :: Linux
Classifier: Programming Language :: Python :: 3
Classifier: Topic :: Scientific/Engineering :: Bio-Informatics
Classifier: Topic :: Scientific/Engineering :: Visualization
Requires-Python: >=3.9
Requires-Dist: customtkinter
Requires-Dist: cycler
Requires-Dist: matplotlib
Requires-Dist: numpy
Requires-Dist: scikit-learn
Requires-Dist: scipy
Requires-Dist: seaborn
Requires-Dist: synergy-file-reader
Requires-Dist: tkextrafont
